{"content":"<!-- wp:canvas\/section {\"canvasClassName\":\"cnvs-block-section-1602924396541\",\"canvasLocation\":\"root\",\"layout\":\"full\"} -->\n<!-- wp:canvas\/section-content {\"canvasClassName\":\"cnvs-block-section-content-1602924410382\",\"canvasLocation\":\"default\",\"paddingTop\":40,\"paddingBottom\":40,\"paddingLeft\":40,\"paddingRight\":40,\"paddingLink\":true,\"backgroundColor\":\"#f8f9fa\",\"backgroundColor_dark\":\"#000000\"} -->\n<!-- wp:canvas\/row {\"canvasClassName\":\"cnvs-block-row-1602924410371\",\"canvasLocation\":\"section-wide\",\"columns\":3} -->\n<!-- wp:canvas\/column {\"canvasClassName\":\"cnvs-block-column-1602924410314\",\"canvasLocation\":\"default\",\"size\":3} -->\n<!-- wp:canvas\/section-heading {\"canvasClassName\":\"cnvs-block-section-heading-1602924410277\",\"canvasLocation\":\"section-sidebar\",\"className\":\"is-style-cnvs-block-section-heading-18 is-style-cnvs-block-section-heading-subheading is-style-cnvs-block-section-subheading\",\"content\":\"Connect\"} \/-->\n\n<!-- wp:canvas\/section-heading {\"canvasClassName\":\"cnvs-block-section-heading-1602924410286\",\"canvasLocation\":\"section-sidebar\",\"className\":\"is-style-cnvs-block-section-heading-1\",\"content\":\"Stay in the Loop\"} \/-->\n\n<!-- wp:canvas\/social-links {\"canvasClassName\":\"cnvs-block-social-links-1602924410303\",\"canvasLocation\":\"section-sidebar\",\"template\":\"inline-alt\",\"showLabels\":false,\"showTitles\":false,\"count\":3} \/-->\n<!-- \/wp:canvas\/column -->\n\n<!-- wp:canvas\/column {\"canvasClassName\":\"cnvs-block-column-1602924410338\",\"canvasLocation\":\"default\",\"size\":5} -->\n<!-- wp:canvas\/opt-in-form {\"canvasClassName\":\"cnvs-block-opt-in-form-1602924410324\",\"canvasLocation\":\"section-content\",\"marginLeft\":40,\"marginTop_tablet\":15,\"marginLeft_tablet\":0,\"marginTop_mobile\":15,\"marginLeft_mobile\":0} \/-->\n<!-- \/wp:canvas\/column -->\n\n<!-- wp:canvas\/column {\"canvasClassName\":\"cnvs-block-column-1602924410359\",\"canvasLocation\":\"default\",\"canvasResponsiveHide_tablet\":true,\"canvasResponsiveHide_mobile\":true,\"size\":4} -->\n<!-- wp:image {\"id\":3082,\"sizeSlug\":\"large\",\"canvasClassName\":\"cnvs-block-core-image-1602924410347\",\"marginTop\":0,\"marginBottom\":-40,\"marginLeft\":60} -->\n<figure class=\"wp-block-image size-large cnvs-block-core-image-1602924410347\"><img src=\"http:\/\/networkertheme.com\/networker\/wp-content\/uploads\/sites\/2\/2020\/10\/nw-banner-mockup.png\" alt=\"\" class=\"wp-image-3082\"\/><\/figure>\n<!-- \/wp:image -->\n<!-- \/wp:canvas\/column -->\n<!-- \/wp:canvas\/row -->\n<!-- \/wp:canvas\/section-content -->\n<!-- \/wp:canvas\/section -->"}
